deeplogix/__init__.py
deeplogix/__main__.py
deeplogix/examples/test-Diffusers-black-forest-labs-FLUX.1-dev.py
deeplogix/examples/test-Diffusers-stable-diffusion-3.5-large.py
deeplogix/examples/test-Transformers-DETR-facebook-detr-resnet-50.py
deeplogix/examples/test-Transformers-LLM-AutoClasses.py
deeplogix/examples/test-Transformers-LLM-pipeline-apply_chat_template.py
deeplogix/examples/test-Transformers-LLM-pipeline.py
deeplogix/examples/test-lungmask.py
deeplogix-0.3.1.dist-info/licenses/LICENCE
deeplogix-0.3.1.dist-info/METADATA
deeplogix-0.3.1.dist-info/WHEEL
deeplogix-0.3.1.dist-info/top_level.txt
deeplogix-0.3.1.dist-info/RECORD
