Metadata-Version: 2.4
Name: deeplogix
Version: 0.3.1
Summary: Deeplogix AI RPC
Author-email: "Alex P." <alexp@deeplogix.io>
Maintainer-email: "Alex P." <alexp@deeplogix.io>
License-Expression: MIT
Keywords: Deeplogix,AI,RPC
Classifier: Programming Language :: Python :: 3
Classifier: Operating System :: OS Independent
Requires-Python: >=3.8
License-File: LICENCE
Dynamic: license-file
